mcp_my_apple_remembers/__init__.py
mcp_my_apple_remembers/__main__.py
mcp_my_apple_remembers/server.py
iflow_mcp_baryhuang_my_apple_remembers-0.1.0.dist-info/METADATA
iflow_mcp_baryhuang_my_apple_remembers-0.1.0.dist-info/WHEEL
iflow_mcp_baryhuang_my_apple_remembers-0.1.0.dist-info/entry_points.txt
iflow_mcp_baryhuang_my_apple_remembers-0.1.0.dist-info/licenses/LICENSE
iflow_mcp_baryhuang_my_apple_remembers-0.1.0.dist-info/RECORD
