Metadata-Version: 2.4
Name: iflow-mcp_baryhuang_my-apple-remembers
Version: 0.1.0
Summary: A simple Apple Remembers MCP server
License-File: LICENSE
Requires-Python: >=3.10
Requires-Dist: mcp>=1.4.1
Requires-Dist: paramiko>=3.5.1
Requires-Dist: python-dotenv>=1.0.1
